<?xml version="1.0" encoding="UTF-8"?>
<!DOCTYPE mapper PUBLIC "-//mybatis.org//DTD Mapper 3.0//EN" "http://mybatis.org/dtd/mybatis-3-mapper.dtd">
<mapper namespace="com.example.demo.domain.mapper.MstUserMapper">
  <resultMap id="BaseResultMap" type="com.example.demo.domain.model.MstUser">
    <!--
      WARNING - @mbg.generated
      This element is automatically generated by MyBatis Generator, do not modify.
      This element was generated on Tue Apr 16 08:58:15 JST 2024.
    -->
    <id column="employee_no" jdbcType="VARCHAR" property="employee_no" />
    <result column="name" jdbcType="VARCHAR" property="name" />
    <result column="name_kana" jdbcType="VARCHAR" property="name_kana" />
    <result column="department" jdbcType="VARCHAR" property="department" />
    <result column="tel_no" jdbcType="VARCHAR" property="tel_no" />
    <result column="mail_adress" jdbcType="VARCHAR" property="mail_adress" />
    <result column="age" jdbcType="INTEGER" property="age" />
    <result column="gender" jdbcType="INTEGER" property="gender" />
    <result column="position" jdbcType="VARCHAR" property="position" />
    <result column="account_level" jdbcType="VARCHAR" property="account_level" />
    <result column="retire_date" jdbcType="DATE" property="retire_date" />
    <result column="register_date" jdbcType="DATE" property="register_date" />
    <result column="update_date" jdbcType="DATE" property="update_date" />
    <result column="delete_flag" jdbcType="BIT" property="delete_flag" />
  </resultMap>
  <sql id="Example_Where_Clause">
    <!--
      WARNING - @mbg.generated
      This element is automatically generated by MyBatis Generator, do not modify.
      This element was generated on Tue Apr 16 08:58:15 JST 2024.
    -->
    <where>
      <foreach collection="oredCriteria" item="criteria" separator="or">
        <if test="criteria.valid">
          <trim prefix="(" prefixOverrides="and" suffix=")">
            <foreach collection="criteria.criteria" item="criterion">
              <choose>
                <when test="criterion.noValue">
                  and ${criterion.condition}
                </when>
                <when test="criterion.singleValue">
                  and ${criterion.condition} #{criterion.value}
                </when>
                <when test="criterion.betweenValue">
                  and ${criterion.condition} #{criterion.value} and #{criterion.secondValue}
                </when>
                <when test="criterion.listValue">
                  and ${criterion.condition}
                  <foreach close=")" collection="criterion.value" item="listItem" open="(" separator=",">
                    #{listItem}
                  </foreach>
                </when>
              </choose>
            </foreach>
          </trim>
        </if>
      </foreach>
    </where>
  </sql>
  <sql id="Update_By_Example_Where_Clause">
    <!--
      WARNING - @mbg.generated
      This element is automatically generated by MyBatis Generator, do not modify.
      This element was generated on Tue Apr 16 08:58:15 JST 2024.
    -->
    <where>
      <foreach collection="example.oredCriteria" item="criteria" separator="or">
        <if test="criteria.valid">
          <trim prefix="(" prefixOverrides="and" suffix=")">
            <foreach collection="criteria.criteria" item="criterion">
              <choose>
                <when test="criterion.noValue">
                  and ${criterion.condition}
                </when>
                <when test="criterion.singleValue">
                  and ${criterion.condition} #{criterion.value}
                </when>
                <when test="criterion.betweenValue">
                  and ${criterion.condition} #{criterion.value} and #{criterion.secondValue}
                </when>
                <when test="criterion.listValue">
                  and ${criterion.condition}
                  <foreach close=")" collection="criterion.value" item="listItem" open="(" separator=",">
                    #{listItem}
                  </foreach>
                </when>
              </choose>
            </foreach>
          </trim>
        </if>
      </foreach>
    </where>
  </sql>
  <sql id="Base_Column_List">
    <!--
      WARNING - @mbg.generated
      This element is automatically generated by MyBatis Generator, do not modify.
      This element was generated on Tue Apr 16 08:58:15 JST 2024.
    -->
    employee_no, name, name_kana, department, tel_no, mail_adress, age, gender, position, 
    account_level, retire_date, register_date, update_date, delete_flag
  </sql>
  <select id="selectByExample" parameterType="com.example.demo.domain.model.MstUserExample" resultMap="BaseResultMap">
    <!--
      WARNING - @mbg.generated
      This element is automatically generated by MyBatis Generator, do not modify.
      This element was generated on Tue Apr 16 08:58:15 JST 2024.
    -->
    select
    <if test="distinct">
      distinct
    </if>
    <include refid="Base_Column_List" />
    from mst_user
    <if test="_parameter != null">
      <include refid="Example_Where_Clause" />
    </if>
    <if test="orderByClause != null">
      order by ${orderByClause}
    </if>
  </select>
  <select id="selectByPrimaryKey" parameterType="java.lang.String" resultMap="BaseResultMap">
    <!--
      WARNING - @mbg.generated
      This element is automatically generated by MyBatis Generator, do not modify.
      This element was generated on Tue Apr 16 08:58:15 JST 2024.
    -->
    select 
    <include refid="Base_Column_List" />
    from mst_user
    where employee_no = #{employee_no,jdbcType=VARCHAR}
  </select>
  <delete id="deleteByPrimaryKey" parameterType="java.lang.String">
    <!--
      WARNING - @mbg.generated
      This element is automatically generated by MyBatis Generator, do not modify.
      This element was generated on Tue Apr 16 08:58:15 JST 2024.
    -->
    delete from mst_user
    where employee_no = #{employee_no,jdbcType=VARCHAR}
  </delete>
  <delete id="deleteByExample" parameterType="com.example.demo.domain.model.MstUserExample">
    <!--
      WARNING - @mbg.generated
      This element is automatically generated by MyBatis Generator, do not modify.
      This element was generated on Tue Apr 16 08:58:15 JST 2024.
    -->
    delete from mst_user
    <if test="_parameter != null">
      <include refid="Example_Where_Clause" />
    </if>
  </delete>
  <insert id="insert" parameterType="com.example.demo.domain.model.MstUser">
    <!--
      WARNING - @mbg.generated
      This element is automatically generated by MyBatis Generator, do not modify.
      This element was generated on Tue Apr 16 08:58:15 JST 2024.
    -->
    insert into mst_user (employee_no, name, name_kana, 
      department, tel_no, mail_adress, 
      age, gender, position, 
      account_level, retire_date, register_date, 
      update_date, delete_flag)
    values (#{employee_no,jdbcType=VARCHAR}, #{name,jdbcType=VARCHAR}, #{name_kana,jdbcType=VARCHAR}, 
      #{department,jdbcType=VARCHAR}, #{tel_no,jdbcType=VARCHAR}, #{mail_adress,jdbcType=VARCHAR}, 
      #{age,jdbcType=INTEGER}, #{gender,jdbcType=INTEGER}, #{position,jdbcType=VARCHAR}, 
      #{account_level,jdbcType=VARCHAR}, #{retire_date,jdbcType=DATE}, #{register_date,jdbcType=DATE}, 
      #{update_date,jdbcType=DATE}, #{delete_flag,jdbcType=BIT})
  </insert>
  <insert id="insertSelective" parameterType="com.example.demo.domain.model.MstUser">
    <!--
      WARNING - @mbg.generated
      This element is automatically generated by MyBatis Generator, do not modify.
      This element was generated on Tue Apr 16 08:58:15 JST 2024.
    -->
    insert into mst_user
    <trim prefix="(" suffix=")" suffixOverrides=",">
      <if test="employee_no != null">
        employee_no,
      </if>
      <if test="name != null">
        name,
      </if>
      <if test="name_kana != null">
        name_kana,
      </if>
      <if test="department != null">
        department,
      </if>
      <if test="tel_no != null">
        tel_no,
      </if>
      <if test="mail_adress != null">
        mail_adress,
      </if>
      <if test="age != null">
        age,
      </if>
      <if test="gender != null">
        gender,
      </if>
      <if test="position != null">
        position,
      </if>
      <if test="account_level != null">
        account_level,
      </if>
      <if test="retire_date != null">
        retire_date,
      </if>
      <if test="register_date != null">
        register_date,
      </if>
      <if test="update_date != null">
        update_date,
      </if>
      <if test="delete_flag != null">
        delete_flag,
      </if>
    </trim>
    <trim prefix="values (" suffix=")" suffixOverrides=",">
      <if test="employee_no != null">
        #{employee_no,jdbcType=VARCHAR},
      </if>
      <if test="name != null">
        #{name,jdbcType=VARCHAR},
      </if>
      <if test="name_kana != null">
        #{name_kana,jdbcType=VARCHAR},
      </if>
      <if test="department != null">
        #{department,jdbcType=VARCHAR},
      </if>
      <if test="tel_no != null">
        #{tel_no,jdbcType=VARCHAR},
      </if>
      <if test="mail_adress != null">
        #{mail_adress,jdbcType=VARCHAR},
      </if>
      <if test="age != null">
        #{age,jdbcType=INTEGER},
      </if>
      <if test="gender != null">
        #{gender,jdbcType=INTEGER},
      </if>
      <if test="position != null">
        #{position,jdbcType=VARCHAR},
      </if>
      <if test="account_level != null">
        #{account_level,jdbcType=VARCHAR},
      </if>
      <if test="retire_date != null">
        #{retire_date,jdbcType=DATE},
      </if>
      <if test="register_date != null">
        #{register_date,jdbcType=DATE},
      </if>
      <if test="update_date != null">
        #{update_date,jdbcType=DATE},
      </if>
      <if test="delete_flag != null">
        #{delete_flag,jdbcType=BIT},
      </if>
    </trim>
  </insert>
  <select id="countByExample" parameterType="com.example.demo.domain.model.MstUserExample" resultType="java.lang.Long">
    <!--
      WARNING - @mbg.generated
      This element is automatically generated by MyBatis Generator, do not modify.
      This element was generated on Tue Apr 16 08:58:15 JST 2024.
    -->
    select count(*) from mst_user
    <if test="_parameter != null">
      <include refid="Example_Where_Clause" />
    </if>
  </select>
  <update id="updateByExampleSelective" parameterType="map">
    <!--
      WARNING - @mbg.generated
      This element is automatically generated by MyBatis Generator, do not modify.
      This element was generated on Tue Apr 16 08:58:15 JST 2024.
    -->
    update mst_user
    <set>
      <if test="row.employee_no != null">
        employee_no = #{row.employee_no,jdbcType=VARCHAR},
      </if>
      <if test="row.name != null">
        name = #{row.name,jdbcType=VARCHAR},
      </if>
      <if test="row.name_kana != null">
        name_kana = #{row.name_kana,jdbcType=VARCHAR},
      </if>
      <if test="row.department != null">
        department = #{row.department,jdbcType=VARCHAR},
      </if>
      <if test="row.tel_no != null">
        tel_no = #{row.tel_no,jdbcType=VARCHAR},
      </if>
      <if test="row.mail_adress != null">
        mail_adress = #{row.mail_adress,jdbcType=VARCHAR},
      </if>
      <if test="row.age != null">
        age = #{row.age,jdbcType=INTEGER},
      </if>
      <if test="row.gender != null">
        gender = #{row.gender,jdbcType=INTEGER},
      </if>
      <if test="row.position != null">
        position = #{row.position,jdbcType=VARCHAR},
      </if>
      <if test="row.account_level != null">
        account_level = #{row.account_level,jdbcType=VARCHAR},
      </if>
      <if test="row.retire_date != null">
        retire_date = #{row.retire_date,jdbcType=DATE},
      </if>
      <if test="row.register_date != null">
        register_date = #{row.register_date,jdbcType=DATE},
      </if>
      <if test="row.update_date != null">
        update_date = #{row.update_date,jdbcType=DATE},
      </if>
      <if test="row.delete_flag != null">
        delete_flag = #{row.delete_flag,jdbcType=BIT},
      </if>
    </set>
    <if test="example != null">
      <include refid="Update_By_Example_Where_Clause" />
    </if>
  </update>
  <update id="updateByExample" parameterType="map">
    <!--
      WARNING - @mbg.generated
      This element is automatically generated by MyBatis Generator, do not modify.
      This element was generated on Tue Apr 16 08:58:15 JST 2024.
    -->
    update mst_user
    set employee_no = #{row.employee_no,jdbcType=VARCHAR},
      name = #{row.name,jdbcType=VARCHAR},
      name_kana = #{row.name_kana,jdbcType=VARCHAR},
      department = #{row.department,jdbcType=VARCHAR},
      tel_no = #{row.tel_no,jdbcType=VARCHAR},
      mail_adress = #{row.mail_adress,jdbcType=VARCHAR},
      age = #{row.age,jdbcType=INTEGER},
      gender = #{row.gender,jdbcType=INTEGER},
      position = #{row.position,jdbcType=VARCHAR},
      account_level = #{row.account_level,jdbcType=VARCHAR},
      retire_date = #{row.retire_date,jdbcType=DATE},
      register_date = #{row.register_date,jdbcType=DATE},
      update_date = #{row.update_date,jdbcType=DATE},
      delete_flag = #{row.delete_flag,jdbcType=BIT}
    <if test="example != null">
      <include refid="Update_By_Example_Where_Clause" />
    </if>
  </update>
  <update id="updateByPrimaryKeySelective" parameterType="com.example.demo.domain.model.MstUser">
    <!--
      WARNING - @mbg.generated
      This element is automatically generated by MyBatis Generator, do not modify.
      This element was generated on Tue Apr 16 08:58:15 JST 2024.
    -->
    update mst_user
    <set>
      <if test="name != null">
        name = #{name,jdbcType=VARCHAR},
      </if>
      <if test="name_kana != null">
        name_kana = #{name_kana,jdbcType=VARCHAR},
      </if>
      <if test="department != null">
        department = #{department,jdbcType=VARCHAR},
      </if>
      <if test="tel_no != null">
        tel_no = #{tel_no,jdbcType=VARCHAR},
      </if>
      <if test="mail_adress != null">
        mail_adress = #{mail_adress,jdbcType=VARCHAR},
      </if>
      <if test="age != null">
        age = #{age,jdbcType=INTEGER},
      </if>
      <if test="gender != null">
        gender = #{gender,jdbcType=INTEGER},
      </if>
      <if test="position != null">
        position = #{position,jdbcType=VARCHAR},
      </if>
      <if test="account_level != null">
        account_level = #{account_level,jdbcType=VARCHAR},
      </if>
      <if test="retire_date != null">
        retire_date = #{retire_date,jdbcType=DATE},
      </if>
      <if test="register_date != null">
        register_date = #{register_date,jdbcType=DATE},
      </if>
      <if test="update_date != null">
        update_date = #{update_date,jdbcType=DATE},
      </if>
      <if test="delete_flag != null">
        delete_flag = #{delete_flag,jdbcType=BIT},
      </if>
    </set>
    where employee_no = #{employee_no,jdbcType=VARCHAR}
  </update>
  <update id="updateByPrimaryKey" parameterType="com.example.demo.domain.model.MstUser">
    <!--
      WARNING - @mbg.generated
      This element is automatically generated by MyBatis Generator, do not modify.
      This element was generated on Tue Apr 16 08:58:15 JST 2024.
    -->
    update mst_user
    set name = #{name,jdbcType=VARCHAR},
      name_kana = #{name_kana,jdbcType=VARCHAR},
      department = #{department,jdbcType=VARCHAR},
      tel_no = #{tel_no,jdbcType=VARCHAR},
      mail_adress = #{mail_adress,jdbcType=VARCHAR},
      age = #{age,jdbcType=INTEGER},
      gender = #{gender,jdbcType=INTEGER},
      position = #{position,jdbcType=VARCHAR},
      account_level = #{account_level,jdbcType=VARCHAR},
      retire_date = #{retire_date,jdbcType=DATE},
      register_date = #{register_date,jdbcType=DATE},
      update_date = #{update_date,jdbcType=DATE},
      delete_flag = #{delete_flag,jdbcType=BIT}
    where employee_no = #{employee_no,jdbcType=VARCHAR}
  </update>
  <select id="selectAll" resultType="com.example.demo.domain.model.MstUser">
    SELECT
        employee_no, name, name_kana, department, tel_no, mail_adress, age, gender, position, account_level, retire_date, register_date, update_date, delete_flag
    FROM
        Mst_User
    WHERE
        delete_flag = False
    ORDER BY
        employee_no ASC
  </select>
  <select id="selectByEmployeeNo" resultType="com.example.demo.domain.model.MstUser">
    SELECT 
        employee_no, name, name_kana, department, tel_no, mail_adress, age, gender, position, account_level, retire_date, register_date, update_date, delete_flag
    FROM 
        MST_USER
    WHERE
        employee_no = #{employeeNo,jdbcType=VARCHAR}
  </select>
  <select id="selectName" resultType="com.example.demo.domain.model.MstUser">
    SELECT 
        name
    FROM 
        MST_USER
    WHERE
        delete_flag = false
  </select>
  <insert id="insertUser" parameterType="com.example.demo.domain.model.MstUser">
    INSERT INTO
        MST_USER(employee_no, name, name_kana, department, tel_no,
        mail_adress, age, gender, position, account_level, retire_date, 
        register_date, update_date, delete_flag)
    VALUES
        (#{employee_no,jdbcType=VARCHAR}, #{name,jdbcType=VARCHAR}, #{name_kana,jdbcType=VARCHAR}, 
        #{department,jdbcType=VARCHAR}, #{tel_no,jdbcType=VARCHAR}, #{mail_adress,jdbcType=VARCHAR}, 
        #{age,jdbcType=INTEGER}, #{gender,jdbcType=INTEGER}, #{position,jdbcType=VARCHAR}, 
        #{account_level,jdbcType=VARCHAR}, #{retire_date,jdbcType=DATE}, #{register_date,jdbcType=DATE}, 
        #{update_date,jdbcType=DATE}, #{delete_flag,jdbcType=BIT})
  </insert>
  <delete id="deleteByEmployeeNo" parameterType="java.lang.String">
    DELETE
    FROM 
        MST_USER
    WHERE
        employee_no = #{employee_no,jdbcType=VARCHAR}
  </delete>
  <delete id="logicalDeleteByEmployeeNo" parameterType="java.lang.String">
    UPDATE 
        MST_USER
    SET
        delete_flag = true
    WHERE
        device_no = #{employee_no,jdbcType=VARCHAR}
  </delete>
  <update id="update" parameterType="com.example.demo.domain.model.MstUser">
    UPDATE 
      MST_USER
    SET 
      name = #{name,jdbcType=VARCHAR},
      name_kana = #{name_kana,jdbcType=VARCHAR},
      department = #{department,jdbcType=VARCHAR},
      tel_no = #{tel_no,jdbcType=VARCHAR},
      mail_adress = #{mail_adress,jdbcType=VARCHAR},
      age = #{age,jdbcType=INTEGER},
      gender = #{gender,jdbcType=INTEGER},
      position = #{position,jdbcType=VARCHAR},
      account_level = #{account_level,jdbcType=VARCHAR},
      retire_date = #{retire_date,jdbcType=DATE},
      register_date = #{register_date,jdbcType=DATE},
      update_date = #{update_date,jdbcType=DATE},
      delete_flag = #{delete_flag,jdbcType=BIT}
    WHERE 
      employee_no = #{employee_no,jdbcType=VARCHAR}
  </update>
</mapper>